setup.cfg
setup.py
BA/__init__.py
BA/beer.py
BA/tools.py
BA/user.py
Beer_Advocate_API.egg-info/PKG-INFO
Beer_Advocate_API.egg-info/SOURCES.txt
Beer_Advocate_API.egg-info/dependency_links.txt
Beer_Advocate_API.egg-info/top_level.txt