Metadata-Version: 1.0
Name: Beer-Advocate-API
Version: 1.1.0
Summary: Beer Advocate API
Home-page: https://github.com/aaronplesset/beer_advocate_api.git
Author: Aaron Plesset
Author-email: aaronplesset@gmail.com
License: Apache License (2.0)
Platform: UNKNOWN
